dls_pmaclib/__init__.py
dls_pmaclib/__main__.py
dls_pmaclib/_version.py
dls_pmaclib/dls_pmacremote.py
dls_pmaclib/dls_pmcpreprocessor.py
dls_pmaclib-3.1.2.dist-info/LICENSE
dls_pmaclib-3.1.2.dist-info/METADATA
dls_pmaclib-3.1.2.dist-info/WHEEL
dls_pmaclib-3.1.2.dist-info/entry_points.txt
dls_pmaclib-3.1.2.dist-info/top_level.txt
dls_pmaclib-3.1.2.dist-info/RECORD
