Metadata-Version: 2.1
Name: dls-pmaclib
Version: 3.1.2
Summary: Python library for communicating with Delta Tau PMACs (both Turbo and Power)
Author-email: James O'Hea <James.OHea@diamond.ac.uk>
License:                                  Apache License
Project-URL: GitHub, https://github.com/DiamondLightSource/dls-pmac-lib
Classifier: Development Status :: 3 - Alpha
Classifier: License :: OSI Approved :: Apache Software License
Classifier: Programming Language :: Python :: 3.10
Classifier: Programming Language :: Python :: 3.11
Classifier: Programming Language :: Python :: 3.12
Requires-Python: >=3.10
License-File: LICENSE
Requires-Dist: pyserial
Requires-Dist: paramiko
Provides-Extra: dev
Requires-Dist: copier; extra == "dev"
Requires-Dist: mypy; extra == "dev"
Requires-Dist: myst-parser; extra == "dev"
Requires-Dist: parameterized; extra == "dev"
Requires-Dist: pipdeptree; extra == "dev"
Requires-Dist: pre-commit; extra == "dev"
Requires-Dist: pydata-sphinx-theme>=0.12; extra == "dev"
Requires-Dist: pytest; extra == "dev"
Requires-Dist: pytest-cov; extra == "dev"
Requires-Dist: ruff; extra == "dev"
Requires-Dist: sphinx-autobuild; extra == "dev"
Requires-Dist: sphinx-copybutton; extra == "dev"
Requires-Dist: sphinx-design; extra == "dev"
Requires-Dist: tox-direct; extra == "dev"
Requires-Dist: types-mock; extra == "dev"
Requires-Dist: types-paramiko; extra == "dev"
